dtcli/__init__.py
dtcli/auth.py
dtcli/cli.py
dtcli/errors.py
dtcli/format.py
dtcli/parser.py
dtcli/table.py
dtcli/args/__init__.py
dtcli/args/claim.py
dtcli/args/config.py
dtcli/args/data_connector.py
dtcli/args/device.py
dtcli/args/emulator.py
dtcli/args/event.py
dtcli/args/organization.py
dtcli/args/project.py
dtcli/args/role.py
dtcli/args/service_account.py
dtcli/commands/__init__.py
dtcli/commands/claim.py
dtcli/commands/config.py
dtcli/commands/data_connector.py
dtcli/commands/device.py
dtcli/commands/emulator.py
dtcli/commands/event.py
dtcli/commands/organization.py
dtcli/commands/project.py
dtcli/commands/role.py
dtcli/commands/service_account.py
dtcli/resources/__init__.py
dtcli/resources/claim.py
dtcli/resources/config.py
dtcli/resources/data_connector.py
dtcli/resources/device.py
dtcli/resources/emulator.py
dtcli/resources/event.py
dtcli/resources/organization.py
dtcli/resources/project.py
dtcli/resources/role.py
dtcli/resources/service_account.py
disruptive_cli-0.5.1.dist-info/LICENSE
disruptive_cli-0.5.1.dist-info/METADATA
disruptive_cli-0.5.1.dist-info/WHEEL
disruptive_cli-0.5.1.dist-info/entry_points.txt
disruptive_cli-0.5.1.dist-info/top_level.txt
disruptive_cli-0.5.1.dist-info/RECORD
