Metadata-Version: 2.1
Name: disruptive-cli
Version: 0.5.1
Summary: Disruptive Technologies CLI.
Home-page: https://github.com/jhgjeraker/disruptive-cli
Author: Johannes H. Gjeraker
Author-email: johannes.holm.gjeraker@disruptive-technologies.com
Project-URL: Developers Page, https://developer.disruptive-technologies.com/docs/
Keywords: disruptive,technologies,dt,api,cli
Classifier: Natural Language :: English
Classifier: License :: OSI Approved :: MIT License
Classifier: Development Status :: 4 - Beta
Classifier: Intended Audience :: Developers
Classifier: Programming Language :: Python :: 3
Classifier: Programming Language :: Python :: 3.8
Classifier: Programming Language :: Python :: 3.9
Classifier: Programming Language :: Python :: 3.10
Classifier: Programming Language :: Python :: 3.11
Classifier: Programming Language :: Python :: 3.12
Classifier: Operating System :: OS Independent
License-File: LICENSE
Requires-Dist: disruptive >=1.6.0
Requires-Dist: pyyaml >=6.0.1
Requires-Dist: types-pyyaml >=6.0.0
Provides-Extra: dev
Requires-Dist: pytest >=7.4.0 ; extra == 'dev'
Requires-Dist: pytest-mock >=3.12.0 ; extra == 'dev'
Requires-Dist: mypy >=1.6.0 ; extra == 'dev'
Requires-Dist: flake8 >=6.1.0 ; extra == 'dev'
Requires-Dist: build >=1.0.0 ; extra == 'dev'
Requires-Dist: setuptools >=68.2.0 ; extra == 'dev'
Requires-Dist: wheel >=0.41.0 ; extra == 'dev'
